[
  {
    "account": "5022294033882327",
    "amount": 4400000
  },
  {
    "account": "5022294032374649",
    "amount": 500000
  },
  {
    "account": "5022294032418230",
    "amount": 875000
  },
  {
    "account": "5022294033780349",
    "amount": 6040000
  },
  {
    "account": "5022294033637499",
    "amount": 50000
  },
  {
    "account": "5022294033781438",
    "amount": 359168000
  },
  {
    "account": "5022294033598790",
    "amount": 2050
  },
  {
    "account": "5022294033116536",
    "amount": 15
  },
  {
    "account": "5022294033678303",
    "amount": 300
  }
]